aurora_term/__init__.py
aurora_term/__main__.py
aurora_term/aurora.py
aurora_term/config.py
aurora_term/terminal.py
aurora_term-0.1.0.dist-info/entry_points.txt
aurora_term-0.1.0.dist-info/LICENSE
aurora_term-0.1.0.dist-info/WHEEL
aurora_term-0.1.0.dist-info/METADATA
aurora_term-0.1.0.dist-info/RECORD
