Metadata-Version: 2.1
Name: aurora-term
Version: 0.1.0
Summary: AWS Aurora Serverless interactive terminal
Home-page: https://github.com/julianolf/aurora-term
License: MIT
Keywords: aws,aurora,data-api,cli
Author: Juliano Fernandes
Author-email: julianofernandes@gmail.com
Requires-Python: >=3.7,<4.0
Classifier: Development Status :: 2 - Pre-Alpha
Classifier: Environment :: Console
Classifier: Intended Audience :: Developers
Classifier: Intended Audience :: System Administrators
Classifier: License :: OSI Approved :: MIT License
Classifier: Operating System :: OS Independent
Classifier: Programming Language :: Python
Classifier: Programming Language :: Python :: 3
Classifier: Programming Language :: Python :: 3.7
Classifier: Programming Language :: Python :: 3.8
Classifier: Topic :: Database
Classifier: Topic :: Utilities
Requires-Dist: boto3 (>=1.10,<2.0)
Requires-Dist: docopt (>=0.6.2,<0.7.0)
Project-URL: Repository, https://github.com/julianolf/aurora-term
